{
  "Text": "文本",
  "部屋のドアが勢いよく開く。<interval=0.4>\nそこにはシゼル＝メがいた――<interval=0.4>\n全身に火傷や裂傷を負った状態で。": "房间的门猛地被推开。<interval=0.4>\n站在那里的正是希泽尔·梅——<interval=0.4>\n浑身遍布烧伤与撕裂伤的状态。",
  "シゼル＝メ？<interval=0.4>　……い、一体どうしたんだ！？": "希泽尔·梅？<interval=0.4>　……你、你究竟怎么了！？",
  "アハハハッ♪　いーっぱいビリッとしてきたの♪\nはぁぁ、すっごくキモチよかったぁ……っ♪": "啊哈哈哈♪人家刚刚被电得噼里啪啦的哦♪\n哈啊～，感觉超级舒服的啦……♪",
  "こんなになるまで戦ってたってことか……！？<interval=0.4>\nとにかく中に入ってくれ！　手当てするから！": "你竟然战斗到这种地步……！？<interval=0.4>\n总之快进来！我来帮你处理伤口！",
  "え～？　そんなのつまんなーい。それより遊ぼーよ～？": "诶～？那样多没意思呀。不如来陪我玩嘛～？",
  "ダメだ！<interval=0.4>　ほら、傷口を洗うからじっとして……！": "不行！<interval=0.4>　来，我要清洗伤口了，乖乖别动……！",
  "濡らしたタオルでシゼル＝メの体を拭い、手当てを試みる。<interval=0.4>\nしかし、流石はヴァイスと言うべきか、<interval=0.2>\nそうしている間に、彼女の傷は急速に癒えていった。": "我用浸湿的毛巾擦拭希泽尔·梅的身体，尝试为她处理伤口。<interval=0.4>\n然而，或许该说不愧是白吧，<interval=0.2>\n就在这期间，她身上的伤口正以惊人的速度愈合着。",
  "……はぁ。<interval=0.4>深い傷はなさそうで、良かった。<interval=0.4>\nまったく……<interval=0.2>冷や汗が出たよ……。": "……呼。<interval=0.4>看来没有太深的伤口，太好了。<interval=0.4>\n真是的……<interval=0.2>我都吓出一身冷汗了……。",
  "汗ぇ～？　……あ、この水のコト？": "汗～？……啊，你是说这些水吗？",
  "シゼル＝メが俺の首筋に顔を寄せ、<interval=0.2>すん、": "希泽尔·梅将脸凑近我的颈侧，<interval=0.2>嗅、",
  "<interval=0.2>と小さく鼻を鳴らす。<interval=0.4>\n――<interval=0.2>生ぬるく、わずかに痺れる感覚が首に走った。": "<interval=0.2>轻轻抽动了一下鼻子。<interval=0.4>\n——<interval=0.2>一股温热、带着轻微麻痹感的触感窜过脖颈。",
  "れろぉっ……♪　アハッ、ビリッとする味ぃ……♪\nね、汗出してよ。もっと飲みたいんだけど。": "舔舔……♪　啊哈，是麻麻的味道呢……♪\n呐，再出点汗嘛。我还想多喝点。",
  "だ、ダメだ、そんなの汚いから！<interval=0.4>\n今すぐ吐き出して――<interval=0.2>": "不、不行，那样太脏了！<interval=0.4>\n快吐出来——<interval=0.2>",
  "ひぅっ！？": "咿呀！？",
  "首筋を流れ落ちる汗。<interval=0.4>": "汗水顺着颈侧滑落。<interval=0.4>",
  "それを追って、シゼル＝メの舌が這う。<interval=0.4>\nゾクゾクする感覚に、思わず息が零れてしまう。": "希泽尔·梅的舌头追着汗迹蜿蜒而上。<interval=0.4>\n酥麻的触感让我不由自主地漏出喘息。",
  "ん、ちゅぅっ……イイ顔ね♪\nニオイも……強くなってきてるぅ……♪": "嗯，啾……表情很棒嘛♪\n气味也……越来越浓了呢……♪",
  "んんっ……舌が届かない……。\n服、邪魔。取っちゃうわね。": "嗯嗯……舌头够不着呢……。\n衣服，碍事。我要脱掉咯。",
  "シゼル＝メが俺の服に指をかける。<interval=0.4>\n": "希泽尔·梅的手指勾住了我的衣襟。<interval=0.4>\n",
  "彼女が少し力を込めると、": "她稍一用力，",
  "それはあっけなく引き裂かれた。": "衣料便轻易地撕裂开来。",
  "あっ……！？": "啊……！？",
  "それじゃ、続きシよっか♪\nん、ちゅっ……じゅるるるっ、はぁぁっ……♪": "那么，继续开动咯♪\n嗯，啾……滋噜噜噜，哈啊……♪",
  "シゼル＝メが俺の上半身に舌を這わせ、吸い上げていく。<interval=0.4>\nくすぐったさに身悶えすれば、肩を掴む力がさらに強まった。": "希泽尔·梅的舌尖在我上半身游走舔舐，随即用力吸吮。<interval=0.4>\n难耐的酥痒感让我扭动身躯，她按住我肩膀的力道又加重了几分。",
  "ん、ちゅるるっ……はぁ。美味し……♪\n……ケド、まだ足んない。もっとビリビリする味は――。": "嗯，滋噜噜……哈啊。好美味……♪\n……但是，还不够。更刺激的味道是——",
  "――あっ♪　ココがあるじゃ～ん♪\nすっごく濃いニオイの……おチンポが♪": "——啊啦♪　原来藏在这里呀～♪\n散发着超浓郁气味的……肉棒呢♪",
  "抵抗も空しく、シゼル＝メがズボンを引き裂く。<interval=0.4>\n": "徒劳的挣扎中，希泽尔·梅撕开了我的裤子。<interval=0.4>\n",
  "その中では、俺の肉棒が緩やかに下着を押し上げていた。": "裤裆里，我的肉棒正将内裤缓缓顶起。",
  "んっ、んんっ、ビリッとするニオイ……たまんなぁい♪\nもう食べちゃうから……あ～ん……♪": "嗯，嗯嗯，这酥麻的气味……受不了啦♪\n我这就开动了哦……啊～嗯……♪",
  "シゼル＝メがおもむろに口を開ける。<interval=0.4>\n熱っぽい吐息がパチパチと弾ける音を立てて空気に溶けた。<interval=0.4>\nたっぷりの唾液が、咥内をてらてらと妖しく潤わせている。": "希泽尔·梅缓缓张开双唇。<interval=0.4>\n滚烫的吐息发出噼啪轻响，在空气中逐渐消散。<interval=0.4>\n丰沛的唾液在她口腔内泛着妖异的光泽，将内部润得湿漉漉的。",
  "――はむっ♪": "——啊呜♪",
  "うああぁっ……！": "呜啊啊啊……！",
  "温泉のような熱さと、心地よさ。<interval=0.4>\nそれに浸る間もなく肉棒全体が吸い上げられる。<interval=0.4>\n直接的な快感に腰がガクガク震え、先端から我慢汁が溢れ出す。": "如同浸泡温泉般的灼热与舒适感。<interval=0.4>\n我还未来得及沉浸其中，整根肉棒就被她深深含住吸吮。<interval=0.4>\n直冲脑髓的快感让我腰肢剧烈颤抖，前端已渗出忍耐不住的先走液。",
  "んふぅぅっ♪　はぁ、ビリビリするぅっ……♪\nもっとお汁出して？　ね、ほらぁっ♪": "嗯呜♪　哈啊、酥酥麻麻的……♪\n再多流些汁水出来嘛？来，快看呐♪",
  "熱い舌が鈴口を容赦なくほじる。<interval=0.4>\n痺れを伴う強すぎる快楽に、思わず体が逃げ出そうとする。<interval=0.4>\nだが腰を強く掴まれ、それすらも叶わない。": "滚烫的舌尖毫不留情地钻探着马眼。<interval=0.4>\n伴随着麻痹感的过度快意，让我的身体下意识想要逃离。<interval=0.4>\n但腰肢被她牢牢钳制，连这微小的挣扎都成了奢望。",
  "はぁっ……んんっ、ぢゅぅぅっ……♪\nんふぅぅ、ぢゅる、ぢゅるるるぅぅっ……♪": "哈啊……嗯嗯、啾呜……♪\n嗯呼、滋噜、滋噜噜噜噜……♪",
  "頬がへこむ勢いでシゼル＝メは肉棒にむしゃぶりつく。<interval=0.4>\n肉幹にべったりと張りついた舌が、裏筋をなぞり上げた。": "希泽尔·梅贪婪地吞吐着肉棒，用力之猛让脸颊都凹陷下去。<interval=0.4>\n紧贴在柱身上的舌头，正沿着系带缓缓向上舔舐。",
  "んっ♪　ここ舐めると、いっぱい出るぅっ……♪\nんむむっ、じゅるっ、ぢゅ、れろぉぉっ……♪": "嗯♪　舔这里的话、会流出好多呢……♪\n嗯唔、滋噜、啾、啵噜噜噜……♪",
  "は、ぅあぁぁっ……！　<interval=0.4>シゼル＝メ、ぐ、うぅぅっ……！": "哈、呜啊啊啊……！　<interval=0.4>希泽尔·梅、咕、呜呜……！",
  "はぁ～……っ。カワイイ顔……♪\n……ふぅぅ、スッゴくビリビリするぅ～……！": "哈啊～……。好可爱的表情……♪\n……呼唔唔，酥麻感超级强烈～……！",
  "――んんんッ！　んむ、ふ、ンン～……っ♪": "――嗯嗯嗯！嗯唔、呼、嗯嗯～……♪",
  "ビクン、<interval=0.2>とシゼル＝メの体が震え、舌がわずかに帯電する。<interval=0.4>\n彼女は悩ましげに眉根を寄せ、脚の間で右手を動かしている。": "希泽尔·梅的身体猛地一颤，<interval=0.2>舌尖传来微弱的带电触感。<interval=0.4>\n她苦恼地蹙起眉头，右手在双腿间不断动作着。",
  "ふぅっ、ん、ふぁあっ……！　あっ、はぁぁっ……♪\nはむ、ぢゅるるっ……むぢゅぅぅっ、んむ、ふぅぅ～……っ！": "呼唔、嗯、哈啊……！啊、哈啊啊……♪\n嗯呣、滋噜噜……嗯啾唔唔、嗯唔、呼唔唔～……！",
  "俺の肉棒をしゃぶりながら、シゼル＝メは自らを慰めていた。<interval=0.4>\nびちゃびちゃと音を立て、愛液がシーツにシミを作る。": "她一边吞吐着我的肉棒，一边慰借着自己。<interval=0.4>\n黏腻的水声不断响起，爱液在床单上晕开深色的痕迹。",
  "ン、ぷはぁっ！　ぢゅる、ぢゅるるるるっ……！\nんんっ、ふぅ～……むぅぅ、ン、ふぅぅ～……んん～ッ！": "嗯、噗哈！滋噜、滋噜噜噜噜……！\n嗯嗯、呼唔～……嗯唔唔、嗯、呼唔唔～……嗯嗯～！",
  "シゼル＝メの興奮に合わせてフェラチオは激しさを増す。<interval=0.4>\n肉棒に絡みつく舌、すぼまった咥内が肉棒を責め立てる。<interval=0.4>\n溶けそうなほど熱い快楽に、腰が勝手に浮き上がってしまう。": "随着希泽尔·梅的兴奋加剧，口交的节奏也愈发激烈。<interval=0.4>\n缠绕在肉棒上的舌尖，紧缩的腔道不断责难着柱身。<interval=0.4>\n近乎融化的炽热快感，让我的腰肢不由自主地向上挺起。",
  "ふ、くぅぅっ……！\nし、シゼル＝メっ……もう、出るっ……！": "呼、咕唔唔……！\n希、希泽尔·梅……要、要去了……！",
  "はぁっ――んっ、ダァ～メ♪\nまだ出しちゃダメ～っ♪": "哈啊――嗯、不～行♪\n现在还不能出来哦～♪",
  "シゼル＝メがぱっと口を離す。<interval=0.4>\n行き場を無くした快楽が、腰の奥でぐるぐると渦巻く。": "希泽尔·梅突然松开了嘴唇。<interval=0.4>\n无处宣泄的快感在腰腹深处盘旋翻涌。",
  "な……なんで？\n出したいっ……出させてくれっ……！": "为……为什么？\n我想射出来……让我射吧……！",
  "アハハッ♪　腰ヘコヘコしちゃって、カワイイ～♪": "啊哈哈♪ 腰都一抽一抽的，好可爱～♪",
  "シゼル＝メが再び俺の肩を掴み、そのままベッドへ押し倒す。<interval=0.4>\n": "希泽尔·梅再次抓住我的肩膀，就这样将我推倒在床上。<interval=0.4>\n",
  "俺に跨ったシゼル＝メは――<interval=0.2>自らの秘所を指で広げた。": "跨坐在我身上的希泽尔·梅——<interval=0.2>用手指撑开了自己的秘处。",
  "見て？\nアタシのおマンコも、まだイッてないんだよ？": "看到了吗？\n我的小穴也还没高潮哦？",
  "蜜口がヒクヒクと切なそうに疼く。<interval=0.4>\nそこからゆっくりと雫が垂れ、俺の頬に落ちた。<interval=0.4>\n濃い雌のフェロモンに、肉棒が痛いほど怒張する。": "蜜穴正一抽一抽地可怜悸动着。<interval=0.4>\n从那里缓缓滴落的蜜液，落在了我的脸颊上。<interval=0.4>\n浓郁的雌性费洛蒙，让我的肉棒硬得发痛。",
  "どーせなら一番ビリビリッ……としたいじゃん？\nだから……出すのは、コ・コ♪": "反正要射的话，当然想在最刺激的时候……对吧？\n所以……要射的话，就射在·这·里♪",
  "シゼル＝メが俺の肉棒に照準を合わせる。\nはち切れんばかりの想いで、俺はそれを凝視する。": "希泽尔·梅将我的肉棒对准了目标。\n带着几乎要爆裂的渴望，我紧紧凝视着那里。",
  "アハハッ♪　鼻息荒～い♪\nチンポ、そんなにビリッとしたいの～？": "啊哈哈♪ 呼吸好粗重呢～♪\n肉棒，就那么想被紧紧包裹吗～？",
  "したい……！　早く入れたい……シゼル＝メ……っ！": "想……！好想快点插进去……希泽尔·梅……！",
  "ふ～ん……♪　そんなカワイイ顔、初めて見たかも。\n……オアズケしたら、もっと見られるかなぁ？": "哼～♪ 这么可爱的表情，说不定还是第一次见到呢。\n……要是让你憋着的话，能看到更多吗～？",
  "！？\nそ、そんなの無理だ！　ここに来てお預けなんて……！": "！？\n这、这怎么可能！都到这一步了还要我憋着……！",
  "腰を持ち上げ、シゼル＝メの中に挿入しようとする。\nしかし――。": "我试图抬起腰，想要插入希泽尔·梅的身体里。\n然而——",
  "ぐああぁっ！？": "咕啊啊啊！？",
  "んうぅっ♪　……勝手なコトしちゃダメよ？\nアンタのチンポは、今、アタシがビリッとするための道具なの。": "嗯呜♪ ……不可以擅自行动哦？\n你的肉棒，现在可是让我酥麻到骨子里的道具呢。",
  "うぅぅ……そ、そんなぁ……っ。": "呜……怎、怎么这样……",
  "んん～～……ッ♪\nはあぁっ……その顔、ビリビリするぅっ……♪": "嗯～～……♪\n哈啊……这副表情，看得我浑身酥麻……♪",
  "あぁ～っ、ダメっ！　オアズケなんて、アタシがムリ！\n――ってコトで……チンポちょ～だい♪　ダ～リンっ♪": "啊～不行！让我憋着什么的，根本做不到啦！\n——所以说……肉棒给我吧♪ 亲·爱·的♪",
  "あはぁぁぁんっ！　あぁ、これぇっ……！\n背筋がビリッとする感じ、たまんなぁい……♪": "啊哈啊啊嗯！啊、这个……！\n脊椎酥麻的感觉，简直受不了……♪",
  "シゼル＝メが飛び跳ねるように大きく腰を振る。\n突然の強い快楽に、息を整えるのもままならず視界が白黒する。": "希泽尔·梅像要跳起来般大幅度摆动腰肢。\n突如其来的强烈快感让我连调整呼吸都做不到，视野开始黑白闪烁。",
  "んんっ、はぁぁっ♪　あぁっ、くぅぅぅん……っ！\nチンポかったぁいっ……♪　オアズケして正解ぃ～っ……♪": "嗯嗯、哈啊♪　啊啊、唔嗯……！\n肉棒好舒服……♪　让你留下来真是对啦～♪",
  "ほらぁ、もっと奥まで突いてぇっ♪\nアタシのナカ、グッチャグチャにしてぇ、んっ、ふぅぅ～っ！": "来嘛、再往更深处顶进来呀♪\n把人家里面搅得乱七八糟吧、嗯、呼唔～！",
  "バチ、バチ、と音を立て、彼女から電撃が迸る。\nその刺激で腰が跳ね、否応なしに肉棒が彼女の膣を突き上げる。": "啪嚓、啪嚓，随着声响，电光从她体内迸发。\n刺激让我的腰肢弹跳起来，肉棒不由分说地向上顶入她的阴道。",
  "あぁぁっ！　イイ～っ……！\nアハハッ、ダーリンもビリッときてんじゃん♪": "啊啊啊！　好舒服～……！\n啊哈哈、亲爱的你也触电般抖了一下嘛♪",
  "うぁぁっ、はぁ、うぐぅっ……！\nシゼル＝メ、もっとゆっくり……っ！": "呜啊啊、哈啊、呜咕……！\n希泽尔·梅、再慢一点……！",
  "はぁっ、あっ、んんっ、ふあぁああぁんっ……！\nあっ、これイイ～……っ！　あぁんっ、あっ、はぁあぁ～んっ！": "哈啊、啊、嗯嗯、呼啊啊啊啊嗯……！\n啊、这个好棒～……！　啊啊嗯、啊、哈啊啊啊～嗯！",
  "シゼル＝メは夢中で肉棒を貪っている。\nカリ首が肉襞に押し込まれ、擦られ、暴力的な快感が俺を襲う。": "希泽尔·梅忘我地贪求着肉棒。\n龟头被肉褶挤压、摩擦，暴力的快感向我袭来。",
  "おぉぉッ……イク、イクゥッ……！　お、ふぅぅ～ん……ッ！\n――はぁっ、あっ、はぁあぁあっ、イイぃ～……ッ！": "哦哦……要去了、要去了……！　哦、呼唔～嗯……！\n――哈啊、啊、哈啊啊啊、好舒服……！",
  "シゼル＝メが体をビクンと跳ねさせる。\n俺の全身に電流が走り、陰嚢から精子が押し出されていく。": "希泽尔·梅的身体猛地一颤。\n电流窜过我的全身，精液从阴囊中被挤压而出。",
  "ふぐぅっ……！　凄い締めつけがっ……！\nシゼル＝メ、俺もイクっ、出る……ッ！": "呼咕……！　这收缩感太强烈了……！\n希泽尔·梅、我也要射了、要出来了……！",
  "はぁぁっ、ん、まだダメぇッ……！\nこんなビリッとするチンポ、んふぅぅっ、離したげないっ……♪": "哈啊～、嗯、还不行……！\n这么酥麻的肉棒、嗯呜～、人家才不要放开呢……♪",
  "<size=32>ぐあぁああっ！！</size>": "<size=32>咕啊啊啊！！</size>",
  "電撃の苦痛で、射精欲が抑えられる。\nしかしトロトロの膣は絶え間なく肉棒を甘やかす。\n痛いのに気持ちいい。混乱した肉棒が、暴れるように猛り立つ。": "电击的痛楚抑制着射精的欲望。\n但湿滑的阴道却持续娇惯着肉棒。\n疼痛中夹杂着快感。混乱的肉棒如同发狂般猛烈勃起。",
  "んぅぅッ！　スゴっ、チンポ跳ねてるぅ……っ！\nあぁぁっ、そぉ、アタシのイイトコ、もっと抉ってぇぇっ♪": "嗯呜！好厉害、肉棒在跳动呢……！\n啊啊～、对、就是那里、再往人家的敏感点顶进去呀～♪",
  "苦痛じみた快楽から解放されたくて、俺は自ら腰を突き上げる。\n俺に跨る彼女が背を逸らし、接合部から愛液が噴き出した。": "为了从痛苦交织的快感中解脱，我主动挺腰向上顶撞。\n骑在我身上的她扭动腰肢，交合处喷溅出爱液。",
  "おほぉぉッ！　イイ、スッゴいイイぃ～ッ！\nはぁぁ、もっと、もっとビリッとしたい、トビたいぃっ……！": "噢噢噢！好棒、超级舒服～！\n哈啊～、还要、还要更强烈的电击、要飞起来了……！",
  "はああぁぁッ！！　アァッ、コレぇっ！！\nこの刺激が欲しかったのぉっ！！　あああっ、はァァ～ッ！！": "哈啊啊啊！！啊、就是这个！！\n人家想要的就是这种刺激呀！！啊啊、哈啊～！！",
  "彼女の腰の動きがますます激しくなる。\nそれと同時に迸る電撃の量も増え、俺の神経を昂らせる。": "她腰部的动作愈发激烈。\n同时迸发的电击量也随之增加，刺激着我的神经不断高涨。",
  "が、あぁっ、シゼル＝メっ、シゼル＝メ……！！": "呃、啊啊、希泽尔·梅、希泽尔·梅……！！",
  "ンン～ッ……！！　あぁっ、チンポしゅごいぃ～っ！！\nカタくてアツくてっ、ずっとビリビリしてるのぉっ……！！": "嗯嗯～！！啊～、肉棒太厉害了～！\n又硬又烫、一直在滋滋放电呢……！！",
  "んふぅぅっ、くっ、お゛ぉぉ～～～ッ！！\nダーリンっ、しゅきぃ、セックスだいしゅきぃっ……！！": "嗯呜～、唔、噢噢噢噢～～～！！\n亲爱的、最喜欢、最喜欢做爱了……！！",
  "俺も好きだっ、シゼル＝メ……ッ！\nはぁっ、ぐ、うぅぅっ……！！": "我也最喜欢、希泽尔·梅……！\n哈啊、咕、呜呜呜……！！",
  "鼻を熱い液体が伝う感覚がするが、そんなことは構わなかった。\n俺は獣のように、一心不乱に目の前の快楽を貪っていた。": "我感觉到温热的液体流过鼻尖，但此刻已无暇顾及。\n我像野兽般忘我地贪求着眼前的欢愉。",
  "あ゛ぁぁっ、イク、イグゥゥっ！！\nしゅっごいビリッとシちゃうぅぅっ……う、くぅぅっ……！！": "啊啊啊、要去了、要去了呜！！\n被电得酥酥麻麻的好厉害呜呜……呜、嗯呜……！！",
  "シゼル＝メが背中を弓なりに反り、ブルブルと震える。\n膣肉が膨らみ、わななき、猛った肉棒がもみくちゃになる。": "希泽尔·梅的脊背弯成弓形，浑身剧烈颤抖着。\n阴道嫩肉随之膨胀震颤，将我那狂躁的肉棒紧紧绞缠。",
  "――はぁ～ッ……！\nイイ～っ……頭の中パチパチするぅ～っ……♪": "——哈啊～……！\n好舒服～……脑袋里噼里啪啦的～……♪",
  "舌から涎を垂らし、シゼル＝メは絶頂の余韻に浸る。\n俺はその膣奥へと、思いきり腰を突き上げた。": "涎水从嘴角垂落，希泽尔·梅仍沉浸在绝顶的余韵中。\n我朝着她阴道深处，用力挺腰顶了上去。",
  "んほぉ゛おぉっ！？　おっ、ほぉぁあっ、はあ゛ぁああぁっ♪\nあ゛ぁあっ、ダーリンしゅごいぃっ、チンポイイぃぃっ！！": "嗯呜噢噢！？ 噢、呜啊啊、哈啊啊啊啊♪\n啊啊啊、亲爱的太厉害了、肉棒好舒服呜呜呜！！",
  "あ゛はぁあ～ッ……あぁあっ、もっと奥突いてぇっ！！\nはあぁぁっ、んふぅううっ、ん、うぅうぅう～～んッ！！": "啊哈啊～……啊啊、再往深处顶呀！！\n哈啊啊、嗯呜呜、嗯、呜呜呜～～嗯！！",
  "イキっぱなしになっている膣内はこれ以上なく気持ちいい。\n動きを止めれば腰砕けになってしまいそうで、\n俺は一心不乱に彼女を責め立て続ける。": "持续高潮的阴道内舒服得无以复加。\n若停下动作恐怕会当场瘫软，\n我只能忘我地继续对她发起责难。",
  "お゛ほぉぉっ、しゅごいっ、奥しゅごいぃぃっ！！\nビリビリ止まんにゃっ、あァッ、んっ、ぐぅぅ～……ッ！！": "呜哦哦哦、好厉害、深处好厉害啊啊啊！！\n电击停不下来啊、啊啊、嗯、咕呜呜～……！！",
  "はあ゛ぁぁッ、またイクぅぅッ……！！\nイッてるのにイクっ、ビリビリしゅごいっ、好きぃぃッ……！！": "哈啊啊啊、又要去了啊啊啊……！！\n明明还在高潮又要去了、电击好厉害、最喜欢了啊啊啊……！！",
  "電撃にせき止められ続けた射精欲もいよいよ限界だった。\n絶対に中出しする。本能のまま、俺は必死に彼女に食らいつく。": "被电击持续抑制的射精欲终于也抵达了极限。\n绝对要内射。遵循本能，我拼命地啃咬着她。",
  "はぁっ……！　シゼル＝メ、俺も出すぞ……！\n今度こそ出す……止められても、絶対中出しするっ……！！": "哈啊……！希泽尔·梅、我也要射了……！\n这次一定要射出来……就算被阻止、也绝对要内射……！！",
  "うんッ、イッてぇ！　せーし全部出してぇっ！！\nアタシもダーリンのせーしで、イ、クぅぅぅんッ……！！": "嗯呜、射进来！把精液全都射进来！！\n我也要用亲爱的的精液、去、去了啊啊啊嗯……！！",
  "はあ゛ぁあぁっ、ほぉ、ん、ふお゛ぉおぉおっ……！！\nダーリンっ、しゅき、しゅきっ……しゅきぃ゛いぃぃっ……！！": "哈啊啊啊啊、呜哦、嗯、呜哦哦哦哦……！！\n亲爱的、最喜欢、最喜欢了……最喜欢啊啊啊……！！",
  "あ゛ぁ～ッ、イクイクイグゥッ、雷落ちるゥッ！！\nはあ゛ぁぁっ、アッ、ア゛ァッ……！\nン、ほお゛ぉおおおぉ～ッ――！！": "啊啊啊～、去了去了去了呜、像被雷劈了一样呜！！\n哈啊啊啊、啊、啊啊啊……！\n嗯、呜哦哦哦哦哦哦～——！！",
  "アハァァッ～……♪　ダーリンのチンポ、すっごぉ……。\nずーっとビクビクしてんじゃーん……♪": "啊哈哈啊～……♪亲爱的的肉棒、好厉害哦……。\n一直在抽搐呢～……♪",
  "彼女の膣が、最後の一滴まで搾り取るように肉棒を締め上げる。\n俺の体は、電撃のせいか絶頂の余韻か、不随意に跳ねていた。": "她的阴道仿佛要榨干最后一滴般紧紧绞缠着我的肉棒。\n不知是因为电击还是高潮的余韵，我的身体正不自觉地痉挛着。",
  "ふ、はぁ……満足できたか、シゼル＝メ？": "呼、哈啊……满足了吗，希泽尔·梅？",
  "アハッ、まあ悪くはなかったケドぉ～……ん？": "啊哈～，倒也不算太差啦～……嗯？",
  "ふーん……？": "唔嗯……？",
  "ダァ～メ。やっぱまだ全然足りなーい。": "不～行。果然还完全不够呢～。",
  "――だからぁ♪\nダーリン、もっといっぱいシよ？": "――所以说呀♪\n亲爱的，再多给我一些嘛？",
  "制止の言葉を吐こうとした唇が塞がれる。<interval=0.4>\n": "我刚想开口制止，嘴唇就被堵住了。<interval=0.4>\n",
  "そのまま熱い舌が俺の口の中をまさぐって、<interval=0.2>\n彼女と、<interval=0.2>俺と、<interval=0.2>ほんの少しの血の匂いが混じり合っていく。": "她滚烫的舌头随即探入我口中翻搅，<interval=0.2>\n她与<interval=0.2>我<interval=0.2>的气息，以及一丝若有若无的血腥味，就这样交融在一起。",
  "……ああ、そうだ。<interval=0.4>彼女はそういうヴァイスだった。<interval=0.4>\nやりたいことをやりたいように押し通す。<interval=0.4>\n俺は彼女のそんなところを、<interval=0.2>眩しいと思ったのだった。": "……啊，对了。<interval=0.4>她就是这样一位维斯。<interval=0.4>\n想做的事就一定要随心所欲地贯彻到底。<interval=0.4>\n而我，<interval=0.2>正是被她这样的地方所深深吸引。"
}