{
  "Text": "文本",
  "その日、": "那一天，",
  "ルルイエに深紅の雪が降った。": "露露耶降下了深红色的雪。",
  "いや、雪じゃない……花びら？": "不，不是雪……是花瓣？",
  "窓から手を伸ばして降り注ぐものを掴み取ると、それは血のように真っ赤に染まった、花の花弁だった。": "我从窗户伸出手，抓住飘落的东西，那是一片被染得如鲜血般赤红的花瓣。",
  "何の花かは分からない。": "我认不出这是什么花。",
  "しかし、こんな街を埋め尽くすほど大量に――しかも、ルルイエの結界を無視して降り注ぐそれが、異様な光景であることは語るまでもない。": "但是，如此大量地——甚至无视露露耶的结界倾泻而下，这般异样的景象已无需多言。",
  "うっ――。": "唔——",
  "不意に、視界が揺らめいた。": "突然，我的视野摇晃起来。",
  "眩暈を起こしたように、頭の中がくらくらする。": "仿佛眩晕一般，我的脑袋昏昏沉沉。",
  "まずい……これは……。": "不妙……这是……",
  "瞼が、鉛のように重くなる。": "我的眼皮，沉重得像灌了铅。",
  "脳みそが考えることを放棄する。": "大脑放弃了思考。",
  "いけないと思っていても、全身を包む倦怠感と、心地の良いまどろみに抗うことができなかった。": "即便知道这样不行，我也无法抵抗那包裹全身的倦怠感，以及令人舒适的昏昏欲睡。",
  "甘い花の香りに包まれて――。": "被甜美的花香包裹着——",
  "意識が――。": "意识——",
  "沈む――。": "沉沦——",
  "――。": "——",
  "……はっ！？": "……哈！？",
  "目覚めると、俺は相変わらずルルイエの自室にいた。": "醒来时，我依然身处露露耶自己的房间。",
  "床板に転がっていた身体を起こすと、身体のあちこちが軋むように痛い。": "从床板上撑起躺倒的身体，浑身上下都像生锈般隐隐作痛。",
  "いったい、どれだけ眠っていたんだろうか。\n命には別状がなさそうだが――。": "我到底睡了多久呢。\n性命倒是无碍——",
  "あ、良かった。\n起きてた。": "啊，太好了。\n你醒了。",
  "ネオン？": "涅安？",
  "部屋の扉があいたかと思えば、ネオンがきょとんとした顔でそこに立っていた。": "房门刚打开，涅安就一脸茫然地站在那里。",
  "起きてた……って、そう言えば赤い花びらが降って来て、それで……。": "醒了……说起来，刚才好像有红色花瓣飘下来，然后……",
  "来て。\n街が変なことになってる。": "快过来。\n街上出怪事了。",
  "変なこと……？": "怪事……？",
  "イマイチ要領を得ないまま、俺はネオンに連れられてルルイエの街へ出る。": "还没完全理解状况，我就被涅安拉着来到了露露耶的街道上。",
  "これは……。": "这是……",
  "そこに広がっていたのは、確かに不可解な光景だった。": "眼前展开的景象，确实令人费解。",
  "街の至る所――道端やお店の中、路肩のベンチなど――至るところに住人たちが横たわっている。": "城镇各处——路边、店铺内、道旁的长椅——到处都躺着居民。",
  "まさかと思って駆けよるが、どうやらみんな眠っているだけのようだった。": "我难以置信地跑过去查看，但大家似乎只是睡着了。",
  "声をかけても、ゆすっても、決して目覚めない。\nとても深い眠りの中だ。": "无论呼唤还是摇晃，都绝不会醒来。\n他们陷入了极深的沉眠。",
  "どういうことだ？": "这到底是怎么回事？",
  "それが分かったらキミを呼んでない。": "要是知道的话，就不会叫醒你了。",
  "それは確かに。": "那倒也是。",
  "しかし、俺だってこの状況を見せられても何がなんだかサッパリだ。": "但是，就算让我看到这种状况，我也完全摸不着头脑。",
  "かろうじて覚えているのは、ルルイエを埋め尽くしたあの『赤』――。": "我勉强记得的，只有那曾覆盖露露耶的『赤红』——",
  "そう言えば、あれだけ降り積もっていた赤い花びらが、街のどこにも影も形も無い。": "说起来，那些曾堆积如山的红色花瓣，如今在城镇里已无影无踪。",
  "あの鮮烈な色も、甘ったるい香りも、手に取るように思い出すことができるのに。": "那抹鲜明的色彩，那股甜腻的香气，至今仍能清晰地回忆起来。",
  "――伏せてっ！": "——趴下！",
  "へっ――。": "诶——",
  "返事をするより先に、ネオンのナタのように巨大な刀の刃面が、俺の目と鼻の先に迫った。": "还没来得及回应，涅安那把如柴刀般巨大的刀刃已迫近我的眼前。",
  "すっころぶようにして慌ててしゃがみ込むと、ぶおんと大きな風切り音が頭上すれすれを通過して――直後に、何かと叩き潰すような鈍い音が背後で響いた。": "我连滚带爬地慌忙蹲下，只听呼嗡一声巨大的破风声擦着头顶掠过——紧接着，身后传来某种东西被砸碎的沉闷声响。",
  "何するんだ、ネオン！？": "你干什么啊，涅安！？",
  "緊急事態だったの！\nそれ！": "紧急情况啦！\n看那个！",
  "言いながら、彼女は刀の切っ先で俺の後ろを指す。": "说着，她用刀尖指向我的身后。",
  "振り返ると、そこには動物……と呼称していいのかどうかも定かではない、異形の怪物の亡骸が横たわっていた。": "回头望去，那里横躺着一具怪物的尸体——说是动物吧，又实在难以确定能否用这个称呼来形容的异形之物。",
  "これは……？": "这是……？",
  "私が知るわけないでしょ。": "我怎么可能知道啦。",
  "……それもそうか。": "……说得也是。",
  "ある種の怖いもの見たさで、俺は改めて怪物に視線を落とす。": "带着某种猎奇心理，我重新将视线投向那怪物。",
  "ルルイエに来てからヘンなモノは、あらかた見尽くした気持ちになっていたが、これはまたそのどれとも似ても似つかない、独特の雰囲気を漂わせている。": "来到璐璐耶后，本以为各种怪奇事物早已见惯不怪，但这家伙却散发着与所见过的任何存在都截然不同的独特气息。",
  "怪物……あえて言うなら、魔物。\nＲＰＧのゲームとかに出て来そうな。": "怪物……硬要形容的话，该说是魔物吧。\n就像RPG游戏里会登场的那种。",
  "――もうひとつ、後ろだ。": "——后面还有一只。",
  "なっ……！？": "什……！？",
  "突然声がしたかと思えば、彼方より手槍のように巨大な矢が、ゴウと音を立てて飛来した。": "突如其来的话音未落，远方已传来破空之声——只见标枪般巨大的箭矢裹挟着呼啸声疾射而来。",
  "矢はそのまま俺とネオンの間を駆け抜けて、これまた背後から迫っていた別の魔物の脳天に突き刺さる。": "箭矢擦着我和涅安之间的空隙掠过，精准贯穿了从背后悄然逼近的另一只魔物的头颅。",
  "ズドン――と、よほど矢の着弾音とはかけ離れた重い音を響かせて、魔物の身体は勢いよく吹き飛び、近くのビルの壁に叩きつけられた。": "随着轰的一声——那绝非寻常箭矢该有的沉重撞击音，魔物的身躯被狠狠震飞，重重砸在附近大楼的外墙上。",
  "ビチャッと嫌な音がして、壁に肉片の染みができる。": "随着令人作呕的啪叽声，墙壁上溅开了一滩肉泥污渍。",
  "起きてる奴がいるとは、驚いた。": "居然还有醒着的人，真是意外。",
  "君は……確か、ルルイエの、えーっと。": "你是……我记得是璐璐耶的，呃——",
  "チンピラをとりまとめてる、\n「スクアーラ・スカーズ」の総長――クアローラ。": "统管街头混混的\n「斯库阿拉之疤」总长——库阿萝拉。",
  "ネオン……！": "涅安……！",
  "良い感じの言葉選びを探していたのに、ネオンが元も子もない言葉で補足してくれた。": "我正斟酌着得体的措辞，涅安却用毫不客气的说法直接补完了介绍。",
  "はみ出し者と言う意味じゃ、ネオン、お前と大差はないぞ。": "要说是局外人的话，涅安，你和我也没多大差别。",
  "おあいにく、私は群れる趣味はないから……それよりも、今はこの状況でしょ？": "真不巧，我可没有扎堆的爱好……比起这个，现在该关注的是眼前的情况吧？",
  "ああ……これは、どういうことだ？\n気を失って目覚めたかと思えば、街の奴らは寝たままだし。\n見知らぬ怪物がルルイエに蔓延っているし。": "啊……这到底，是怎么回事？\n刚以为昏迷后醒来，结果城里的人还都睡着。\n陌生的怪物又在璐璐耶到处蔓延。",
  "分かってたら、こんなとこうろついてないでどうにかしてる。\n……でしょ？": "要是知道原因，我们也不会在这儿瞎转悠了。\n……对吧？",
  "あ、ああ。": "啊、啊啊。",
  "そうか……スカーズの奴らも同じ状況だ。\n何か、手がかりがあればと思ったが。": "这样啊……斯库阿拉那帮家伙也是同样的情况。\n我还想着，要是有什么线索就好了。",
  "手がかりがないなら、探すしかない。\n幸いなことに、動けるのが少なくとも３人はここにいるし。": "没有线索的话，就只能去找了。\n幸运的是，至少能动弹的三人都在这里。",
  "街を調べれば、もっと他にも居るかもしれない。": "调查一下街道的话，说不定还有更多能动的人。",
  "そうだな。\n何が起きてるのか、確かめないことには。": "说得对。\n不先确认一下发生了什么可不行。",
  "クアローラも、力を貸してくれないか？\n少なくとも、ルルイエの街に関しては俺なんかより詳しいだろうし。": "库阿萝拉，你也能助我们一臂之力吗？\n至少，关于璐璐耶的街道，你肯定比我这种人要熟悉得多。",
  "……仲間のためだ、仕方ないか。": "……为了同伴，没办法呢。",
  "分かった。\nできる限りで手を貸そう。": "明白了。\n我会尽我所能帮忙的。",
  "俺たちは「謎の眠り病」に犯されたルルイエへと繰り出す――。": "我们朝着被「谜之昏睡病」侵袭的璐璐耶进发——。"
}